{
  "projets": [
    {
      "id": "6731",
      "title": "mosquee",
      "desc": "hasane 2",
      "url": "https://th.bing.com/th/id/OIP.Agnw4evPNUjMo1VWWZiagAHaEq?w=315&h=198&c=7&r=0&o=7&dpr=1.1&pid=1.7&rm=3"
    },
    {
      "id": "fa4e",
      "title": "saxdsvsd",
      "desc": "qas",
      "url": "https://th.bing.com/th/id/OIP.Agnw4evPNUjMo1VWWZiagAHaEq?w=315&h=198&c=7&r=0&o=7&dpr=1.1&pid=1.7&rm=3"
    },
    {
      "id": "d821",
      "title": "hhhh",
      "desc": "h",
      "url": "https://th.bing.com/th/id/OIP.Agnw4evPNUjMo1VWWZiagAHaEq?w=315&h=198&c=7&r=0&o=7&dpr=1.1&pid=1.7&rm=3"
    }
  ]
}